boxit/__init__.py
boxit/boxit.py
boxit-1.0.0.dist-info/METADATA
boxit-1.0.0.dist-info/WHEEL
boxit-1.0.0.dist-info/top_level.txt
boxit-1.0.0.dist-info/RECORD
