Metadata-Version: 2.1
Name: boxit
Version: 1.0.0
Summary: A CLI utility to make your text stand out
Home-page: https://github.com/shivampandya/boxit
Author: Shivam Pandya
Author-email: shivamnyt@gmail.com
License: UNKNOWN
Keywords: python,boxit,text color,tabular,ascii,box
Platform: UNKNOWN
Classifier: License :: OSI Approved :: GNU General Public License v3 (GPLv3)
Classifier: Development Status :: 1 - Planning
Classifier: Intended Audience :: Developers
Classifier: Programming Language :: Python :: 3
Classifier: Operating System :: Unix
Classifier: Operating System :: MacOS :: MacOS X
Classifier: Operating System :: Microsoft :: Windows
